vivideo/__init__.py
vivideo/align.py
vivideo/edit.py
vivideo/transcribe.py
vivideo-0.0.1.dist-info/METADATA
vivideo-0.0.1.dist-info/WHEEL
vivideo-0.0.1.dist-info/entry_points.txt
vivideo-0.0.1.dist-info/licenses/LICENSE
vivideo-0.0.1.dist-info/RECORD
