Metadata-Version: 2.1
Name: vivideo
Version: 0.0.1
Summary: Edit videos with a text editor
Project-URL: Homepage, https://github.com/jbochi/vi-video
Project-URL: Bug Tracker, https://github.com/jbochi/vi-video/issues
Author-email: Juarez Bochi <jbochi@gmail.com>
License-File: LICENSE
Classifier: License :: OSI Approved :: MIT License
Classifier: Operating System :: OS Independent
Classifier: Programming Language :: Python :: 3
Requires-Python: >=3.7
